pyRofex/__init__.py
pyRofex/service.py
pyRofex/clients/__init__.py
pyRofex/clients/rest_rfx.py
pyRofex/clients/websocket_rfx.py
pyRofex/components/__init__.py
pyRofex/components/enums.py
pyRofex/components/exceptions.py
pyRofex/components/globals.py
pyRofex/components/messages.py
pyRofex/components/urls.py
pyRofex-0.5.0.dist-info/LICENSE
pyRofex-0.5.0.dist-info/METADATA
pyRofex-0.5.0.dist-info/WHEEL
pyRofex-0.5.0.dist-info/top_level.txt
pyRofex-0.5.0.dist-info/RECORD
