Metadata-Version: 2.1
Name: pyRofex
Version: 0.5.0
Summary: Python connector for ROFEX's Rest and Websocket APIs.
Home-page: https://github.com/gruporofex/pyRofex
Author: Franco Zanuso
Author-email: francozanuso89@gmail.com
Classifier: Programming Language :: Python :: 3
Classifier: License :: OSI Approved :: MIT License
Classifier: Operating System :: OS Independent
Classifier: Development Status :: 4 - Beta
Classifier: Intended Audience :: Developers
Classifier: Intended Audience :: Information Technology
Classifier: Intended Audience :: Science/Research
Classifier: Topic :: Office/Business :: Financial :: Investment
Classifier: Topic :: Software Development
License-File: LICENSE
Requires-Dist: requests >=2.20.0
Requires-Dist: simplejson >=3.10.0
Requires-Dist: enum34 >=1.1.6
Requires-Dist: websocket-client >=1.6.4
